Metadata-Version: 1.0
Name: gparser
Version: 0.1.1
Summary: am expressive parser library
Home-page: https://github.com/zhongzc/gparser
Author: Gaufoo
Author-email: zhongzc_arch@outlook.com
License: MIT License
Platform: UNKNOWN
